digwebs/__init__.py
digwebs/apis.py
digwebs/body_parser.py
digwebs/common.py
digwebs/errors.py
digwebs/favicon.ico
digwebs/project_generator.py
digwebs/request.py
digwebs/response.py
digwebs/response_code.py
digwebs/router.py
digwebs/template.py
digwebs/web.py
digwebs-0.0.1.dist-info/LICENSE
digwebs-0.0.1.dist-info/METADATA
digwebs-0.0.1.dist-info/WHEEL
digwebs-0.0.1.dist-info/entry_points.txt
digwebs-0.0.1.dist-info/top_level.txt
digwebs-0.0.1.dist-info/RECORD
