Metadata-Version: 2.1
Name: digwebs
Version: 0.0.1
Summary: A tiny web framework-digwebs 
Home-page: https://github.com/digolds/digwebs
Author: SLZ
Author-email: founders@digolds.cn
License: UNKNOWN
Platform: UNKNOWN
Classifier: Programming Language :: Python :: 3
Classifier: License :: OSI Approved :: MIT License
Classifier: Operating System :: OS Independent
Requires-Python: >=3.6
